pcreate/__init__.py
pcreate/create_project.py
PCreate-0.2.dist-info/METADATA
PCreate-0.2.dist-info/WHEEL
PCreate-0.2.dist-info/entry_points.txt
PCreate-0.2.dist-info/top_level.txt
PCreate-0.2.dist-info/RECORD
