Metadata-Version: 2.1
Name: PCreate
Version: 0.2
Summary: A package to quickly initialize Python projects
Home-page: https://github.com/sarthak09walia/pcreate
Author: Sarthak Walia
Author-email: waliasarthak0009@gmail.com
License: MIT
Classifier: Programming Language :: Python :: 3
Classifier: License :: OSI Approved :: MIT License
Classifier: Operating System :: OS Independent
Requires-Python: >=3.6
